{
	"info": {
		"_postman_id": "30b3699b-7e03-4c15-83ab-f49ddde0575f",
		"name": "PETSTORE_Shabatska",
		"schema": "https://schema.getpostman.com/json/collection/v2.1.0/collection.json",
		"_exporter_id": "29414530"
	},
	"item": [
		{
			"name": "Precondition Add a new pet to the store",
			"event": [
				{
					"listen": "test",
					"script": {
						"exec": [
							"pm.test(\"Status code is 200\", function () {\r",
							"    pm.response.to.have.status(200);\r",
							"});\r",
							"\r",
							"\r",
							"var jsonData = pm.response.json();\r",
							"console.log (jsonData.id);\r",
							"pm.collectionVariables.set(\"petId\", jsonData.id);"
						],
						"type": "text/javascript"
					}
				}
			],
			"request": {
				"method": "POST",
				"header": [],
				"body": {
					"mode": "raw",
					"raw": "{\r\n  \"id\": 0,\r\n  \"category\": {\r\n    \"id\": 0,\r\n    \"name\": \"cat\"\r\n  },\r\n  \"name\": \"nyusia\",\r\n  \"photoUrls\": [\r\n    \"string\"\r\n  ],\r\n  \"tags\": [\r\n    {\r\n      \"id\": 0,\r\n      \"name\": \"string\"\r\n    }\r\n  ],\r\n  \"status\": \"available\"\r\n}",
					"options": {
						"raw": {
							"language": "json"
						}
					}
				},
				"url": {
					"raw": "https://petstore.swagger.io/v2/pet",
					"protocol": "https",
					"host": [
						"petstore",
						"swagger",
						"io"
					],
					"path": [
						"v2",
						"pet"
					]
				}
			},
			"response": []
		},
		{
			"name": "Add a new pet to the store",
			"event": [
				{
					"listen": "test",
					"script": {
						"exec": [
							"pm.test(\"Status code is 200\", function () {\r",
							"    pm.response.to.have.status(200);\r",
							"});\r",
							"\r",
							"\r",
							"pm.test(\"Check Pet Id\", function () {\r",
							"    var jsonData = pm.response.json();\r",
							"    //console.log(jsonData.category.name);\r",
							"    pm.expect(jsonData.category.name).to.eql('cat');\r",
							"    //console.log(jsonData.name);\r",
							"    pm.expect(jsonData.name).to.eql('nyusia');\r",
							"    pm.expect(jsonData.status).to.eql('available');\r",
							"});\r",
							"\r",
							"pm.test(\"Negative test Check Pet Status\", function () {\r",
							"    var jsonData = pm.response.json();\r",
							"    console.log(jsonData.status);\r",
							"    pm.expect(jsonData.status).to.eql('sold');\r",
							"});\r",
							"\r",
							"pm.test(\"Negative test Check notValid pet name\", function () {\r",
							"    var jsonData = pm.response.json();\r",
							"    pm.expect(jsonData.name).to.eql('pesyk');\r",
							"});"
						],
						"type": "text/javascript"
					}
				}
			],
			"request": {
				"method": "POST",
				"header": [],
				"body": {
					"mode": "raw",
					"raw": "{\r\n  \"id\": 0,\r\n  \"category\": {\r\n    \"id\": 0,\r\n    \"name\": \"cat\"\r\n  },\r\n  \"name\": \"nyusia\",\r\n  \"photoUrls\": [\r\n    \"string\"\r\n  ],\r\n  \"tags\": [\r\n    {\r\n      \"id\": 0,\r\n      \"name\": \"string\"\r\n    }\r\n  ],\r\n  \"status\": \"available\"\r\n}",
					"options": {
						"raw": {
							"language": "json"
						}
					}
				},
				"url": {
					"raw": "https://petstore.swagger.io/v2/pet",
					"protocol": "https",
					"host": [
						"petstore",
						"swagger",
						"io"
					],
					"path": [
						"v2",
						"pet"
					]
				}
			},
			"response": []
		},
		{
			"name": "Add a new pet to the store Invalid input request",
			"event": [
				{
					"listen": "test",
					"script": {
						"exec": [
							"pm.test(\"Status code is 405\", function () {\r",
							"    pm.response.to.have.status(405);\r",
							"});"
						],
						"type": "text/javascript"
					}
				}
			],
			"request": {
				"method": "POST",
				"header": [],
				"body": {
					"mode": "raw",
					"raw": "{\r\n  \"id\": 0,\r\n  \"category\": {\r\n    \"id\": 0,\r\n    \"name\": \"cat\"\r\n  },\r\n  \"name\": \"nyusia\",\r\n  \"photoUrls\": [\r\n    \"string\"\r\n  ],\r\n  \"tags\": [\r\n    {\r\n      \"id\": 0,\r\n      \"name\": \"string\"\r\n    }\r\n  ],\r\n  \"status\": \"available\"\r\n}",
					"options": {
						"raw": {
							"language": "json"
						}
					}
				},
				"url": {
					"raw": "https://petstore.swagger.io",
					"protocol": "https",
					"host": [
						"petstore",
						"swagger",
						"io"
					]
				}
			},
			"response": []
		},
		{
			"name": "Add a new pet to the store Invalid input http",
			"event": [
				{
					"listen": "test",
					"script": {
						"exec": [
							"pm.test(\"Status code is 405\", function () {\r",
							"    pm.response.to.have.status(405);\r",
							"});"
						],
						"type": "text/javascript"
					}
				}
			],
			"request": {
				"method": "POST",
				"header": [],
				"body": {
					"mode": "raw",
					"raw": "{\r\n  \"id\": 0,\r\n  \"category\": {\r\n    \"id\": 0,\r\n    \"name\": \"cat\"\r\n  },\r\n  \"name\": \"nyusia\",\r\n  \"photoUrls\": [\r\n    \"string\"\r\n  ],\r\n  \"tags\": [\r\n    {\r\n      \"id\": 0,\r\n      \"name\": \"string\"\r\n    }\r\n  ],\r\n  \"status\": \"available\"\r\n}",
					"options": {
						"raw": {
							"language": "json"
						}
					}
				},
				"url": {
					"raw": "http://petstore.swagger.io/v2/pet",
					"protocol": "http",
					"host": [
						"petstore",
						"swagger",
						"io"
					],
					"path": [
						"v2",
						"pet"
					]
				}
			},
			"response": []
		},
		{
			"name": "Update an existing pet",
			"event": [
				{
					"listen": "test",
					"script": {
						"exec": [
							"pm.test(\"Status code is 200\", function () {\r",
							"    pm.response.to.have.status(200);\r",
							"});\r",
							"\r",
							"\r",
							"pm.test(\"Check Pet Id\", function () {\r",
							"    var jsonData = pm.response.json();\r",
							"    //console.log(jsonData.category.name);\r",
							"    pm.expect(jsonData.category.name).to.eql('cat');\r",
							"    //console.log(jsonData.name);\r",
							"    pm.expect(jsonData.name).to.eql('nyusia2');\r",
							"    pm.expect(jsonData.status).to.eql('available');\r",
							"});\r",
							"\r",
							"pm.test(\"Negative test Check Pet Status\", function () {\r",
							"    var jsonData = pm.response.json();\r",
							"    console.log(jsonData.status);\r",
							"    pm.expect(jsonData.status).to.eql('sold');\r",
							"});\r",
							"\r",
							"pm.test(\"Negative test Check notValid pet name\", function () {\r",
							"    var jsonData = pm.response.json();\r",
							"    pm.expect(jsonData.name).to.eql('pesyk2');\r",
							"});\r",
							"\r",
							"pm.test(\"Negative test Check notValid pet id\", function () {\r",
							"    var jsonData = pm.response.json();\r",
							"    pm.expect(jsonData.id).to.eql(922337203685476);\r",
							"});"
						],
						"type": "text/javascript"
					}
				}
			],
			"request": {
				"method": "PUT",
				"header": [],
				"body": {
					"mode": "raw",
					"raw": "{\r\n  \"id\": 9223372036854763301,\r\n  \"category\": {\r\n    \"id\": 0,\r\n    \"name\": \"cat\"\r\n  },\r\n  \"name\": \"nyusia2\",\r\n  \"photoUrls\": [\r\n    \"string\"\r\n  ],\r\n  \"tags\": [\r\n    {\r\n      \"id\": 0,\r\n      \"name\": \"string\"\r\n    }\r\n  ],\r\n  \"status\": \"available\"\r\n}",
					"options": {
						"raw": {
							"language": "json"
						}
					}
				},
				"url": {
					"raw": "https://petstore.swagger.io/v2/pet",
					"protocol": "https",
					"host": [
						"petstore",
						"swagger",
						"io"
					],
					"path": [
						"v2",
						"pet"
					]
				}
			},
			"response": []
		},
		{
			"name": "Update an existing pet with Invalid Id",
			"event": [
				{
					"listen": "test",
					"script": {
						"exec": [
							"pm.test(\"Status code is 400\", function () {\r",
							"    pm.response.to.have.status(400);\r",
							"});\r",
							"\r",
							"pm.test(\"Check response\", function () {\r",
							"    var jsonData = pm.response.json();\r",
							"    pm.expect(jsonData.message).to.eql('Invalid ID supplied');\r",
							"});"
						],
						"type": "text/javascript"
					}
				}
			],
			"request": {
				"method": "PUT",
				"header": [],
				"body": {
					"mode": "raw",
					"raw": "{\r\n  \"id\": 9223372036854763301%,\r\n  \"category\": {\r\n    \"id\": 0,\r\n    \"name\": \"cat\"\r\n  },\r\n  \"name\": \"nyusia2\",\r\n  \"photoUrls\": [\r\n    \"string\"\r\n  ],\r\n  \"tags\": [\r\n    {\r\n      \"id\": 0,\r\n      \"name\": \"string\"\r\n    }\r\n  ],\r\n  \"status\": \"available\"\r\n}",
					"options": {
						"raw": {
							"language": "json"
						}
					}
				},
				"url": {
					"raw": "https://petstore.swagger.io/v2/pet",
					"protocol": "https",
					"host": [
						"petstore",
						"swagger",
						"io"
					],
					"path": [
						"v2",
						"pet"
					]
				}
			},
			"response": []
		},
		{
			"name": "Finds Pets by status",
			"event": [
				{
					"listen": "test",
					"script": {
						"exec": [
							"pm.test(\"Status code is 200\", function () {\r",
							"    pm.response.to.have.status(200);\r",
							"});"
						],
						"type": "text/javascript"
					}
				}
			],
			"request": {
				"method": "GET",
				"header": [],
				"url": {
					"raw": "https://petstore.swagger.io/v2/pet/findByStatus?status=available",
					"protocol": "https",
					"host": [
						"petstore",
						"swagger",
						"io"
					],
					"path": [
						"v2",
						"pet",
						"findByStatus"
					],
					"query": [
						{
							"key": "status",
							"value": "available"
						}
					]
				}
			},
			"response": []
		},
		{
			"name": "Finds Pets by INVALID status",
			"event": [
				{
					"listen": "test",
					"script": {
						"exec": [
							"pm.test(\"Status code is 400\", function () {\r",
							"    pm.response.to.have.status(400);\r",
							"});\r",
							"\r",
							"pm.test(\"Check response\", function () {\r",
							"    var jsonData = pm.response.json();\r",
							"    pm.expect(jsonData.message).to.eql('Invalid status value');\r",
							"});"
						],
						"type": "text/javascript"
					}
				}
			],
			"request": {
				"method": "GET",
				"header": [],
				"url": {
					"raw": "https://petstore.swagger.io/v2/pet/findByStatus?status=%%%345",
					"protocol": "https",
					"host": [
						"petstore",
						"swagger",
						"io"
					],
					"path": [
						"v2",
						"pet",
						"findByStatus"
					],
					"query": [
						{
							"key": "status",
							"value": "%%%345"
						}
					]
				}
			},
			"response": []
		},
		{
			"name": "Find VALID pet by ID",
			"event": [
				{
					"listen": "test",
					"script": {
						"exec": [
							"pm.test(\"Status code is 200\", function () {\r",
							"    pm.response.to.have.status(200);\r",
							"});\r",
							"\r",
							"pm.test(\"Check Find Pet by Id\", function () {\r",
							"    var jsonData = pm.response.json();\r",
							"    pm.expect(jsonData.id).to.eql(9223372036854762961);\r",
							"    pm.expect(jsonData.category.name).to.eql('cat');\r",
							"    pm.expect(jsonData.name).to.eql('nyusia2');\r",
							"    pm.expect(jsonData.status).to.eql('available');\r",
							"});\r",
							"\r",
							"pm.test(\"Negative test Check INVALID pet name\", function () {\r",
							"    var jsonData = pm.response.json();\r",
							"    pm.expect(jsonData.name).to.eql('pesyk');\r",
							"});\r",
							"\r",
							"pm.test(\"Negative test Check INVALID Category name\", function () {\r",
							"    var jsonData = pm.response.json();\r",
							"    pm.expect(jsonData.category.name).to.eql('dog');\r",
							"});\r",
							"\r",
							"pm.test(\"Negative test Check INVALID status\", function () {\r",
							"    var jsonData = pm.response.json();\r",
							"    pm.expect(jsonData.status).to.eql('sold');\r",
							"});"
						],
						"type": "text/javascript"
					}
				}
			],
			"request": {
				"method": "GET",
				"header": [],
				"url": {
					"raw": "https://petstore.swagger.io/v2/pet/9223372036854762961",
					"protocol": "https",
					"host": [
						"petstore",
						"swagger",
						"io"
					],
					"path": [
						"v2",
						"pet",
						"9223372036854762961"
					]
				}
			},
			"response": []
		},
		{
			"name": "Find NON EXIST pet by INVALID ID",
			"event": [
				{
					"listen": "test",
					"script": {
						"exec": [
							"pm.test(\"Status code is 400\", function () {\r",
							"    pm.response.to.have.status(400);\r",
							"});\r",
							"\r",
							"pm.test(\"Check response\", function () {\r",
							"    var jsonData = pm.response.json();\r",
							"    pm.expect(jsonData.message).to.eql('Invalid ID supplied');\r",
							"});"
						],
						"type": "text/javascript"
					}
				}
			],
			"request": {
				"method": "GET",
				"header": [],
				"url": {
					"raw": "https://petstore.swagger.io/v2/pet/0%",
					"protocol": "https",
					"host": [
						"petstore",
						"swagger",
						"io"
					],
					"path": [
						"v2",
						"pet",
						"0%"
					]
				}
			},
			"response": []
		},
		{
			"name": "Find NON EXIST pet by notExisting ID",
			"event": [
				{
					"listen": "test",
					"script": {
						"exec": [
							"pm.test(\"Status code is 404\", function () {\r",
							"    pm.response.to.have.status(404);\r",
							"});\r",
							"\r",
							"pm.test(\"Check response\", function () {\r",
							"    var jsonData = pm.response.json();\r",
							"    pm.expect(jsonData.message).to.eql('Pet not found');\r",
							"});"
						],
						"type": "text/javascript"
					}
				}
			],
			"request": {
				"method": "GET",
				"header": [],
				"url": {
					"raw": "https://petstore.swagger.io/v2/pet/922337203685476330",
					"protocol": "https",
					"host": [
						"petstore",
						"swagger",
						"io"
					],
					"path": [
						"v2",
						"pet",
						"922337203685476330"
					]
				}
			},
			"response": []
		},
		{
			"name": "Deletes a pet",
			"event": [
				{
					"listen": "test",
					"script": {
						"exec": [
							"pm.test(\"Status code is 200\", function () {\r",
							"    pm.response.to.have.status(200);\r",
							"});\r",
							"\r",
							""
						],
						"type": "text/javascript"
					}
				}
			],
			"request": {
				"method": "DELETE",
				"header": [],
				"url": {
					"raw": "https://petstore.swagger.io/v2/pet/9223372036854763301",
					"protocol": "https",
					"host": [
						"petstore",
						"swagger",
						"io"
					],
					"path": [
						"v2",
						"pet",
						"9223372036854763301"
					]
				}
			},
			"response": []
		},
		{
			"name": "Deletes a pet with INVALID ID",
			"event": [
				{
					"listen": "test",
					"script": {
						"exec": [
							"pm.test(\"Status code is 404\", function () {\r",
							"    pm.response.to.have.status(404);\r",
							"});\r",
							"\r",
							"pm.test(\"Check response\", function () {\r",
							"    var jsonData = pm.response.json();\r",
							"    pm.expect(jsonData.code).to.eql(404);\r",
							"    pm.expect(jsonData.message).to.eql('Pet not found');\r",
							"});\r",
							"\r",
							"\r",
							""
						],
						"type": "text/javascript"
					}
				}
			],
			"request": {
				"method": "DELETE",
				"header": [],
				"url": {
					"raw": "https://petstore.swagger.io/v2/pet/9223372036854763301_",
					"protocol": "https",
					"host": [
						"petstore",
						"swagger",
						"io"
					],
					"path": [
						"v2",
						"pet",
						"9223372036854763301_"
					]
				}
			},
			"response": []
		}
	],
	"event": [
		{
			"listen": "prerequest",
			"script": {
				"type": "text/javascript",
				"exec": [
					""
				]
			}
		},
		{
			"listen": "test",
			"script": {
				"type": "text/javascript",
				"exec": [
					""
				]
			}
		}
	],
	"variable": [
		{
			"key": "petID",
			"value": ""
		},
		{
			"key": "petId",
			"value": ""
		}
	]
}